[{
	"id": 13,
	"content": "Was actively involved in applying skills and knowledge to meet community needs",
	"identifier": "A",
	"attributes": "{ civicProfessional: true }",
	"questionId": 11
}, {
	"id": 14,
	"content": "Had to balance a variety of commitments, including supporting causes that matter to me",
	"identifier": "B",
	"attributes": "{ civicProfessional: true }",
	"questionId": 11
}, {
	"id": 15,
	"content": "Took advantage of classes and other opportunities that offered the chance to get hands-on experience",
	"identifier": "C",
	"attributes": "{ civicProfessional: true }",
	"questionId": 11
}, {
	"id": 16,
	"content": "Mostly ate pizza and took naps",
	"identifier": "D",
	"attributes": "{ civicProfessional: false }",
	"questionId": 11
}, {
	"id": 17,
	"content": "Draw on past experiences that have helped me learn to work in teams",
	"identifier": "A",
	"attributes": "{ civicProfessional: true }",
	"questionId": 12
}, {
	"id": 18,
	"content": "Think about a time when I have done that through community engagement",
	"identifier": "B",
	"attributes": "{ civicProfessional: true }",
	"questionId": 12
}, {
	"id": 19,
	"content": "Have learned how to listen, ask questions, and make the best of the situation",
	"identifier": "C",
	"attributes": "{ civicProfessional: true }",
	"questionId": 12
}, {
	"id": 20,
	"content": "Run away",
	"identifier": "D",
	"attributes": "{ civicProfessional: false }",
	"questionId": 12
}, {
	"id": 21,
	"content": "Research it and determine the best way to get involved",
	"identifier": "A",
	"attributes": "{ civicProfessional: true }",
	"questionId": 13
}, {
	"id": 22,
	"content": "Think about ways I have seen others make a difference and ask how I can help",
	"identifier": "B",
	"attributes": "{ civicProfessional: true }",
	"questionId": 13
}, {
	"id": 23,
	"content": "Determine the skills I can most uniquely contribute",
	"identifier": "C",
	"attributes": "{ civicProfessional: true }",
	"questionId": 13
}, {
	"id": 24,
	"content": "Ignore it",
	"identifier": "D",
	"attributes": "{ civicProfessional: false }",
	"questionId": 13
}, {
	"id": 25,
	"content": "Apply the knowledge and skills I have from past experiences",
	"identifier": "A",
	"attributes": "{ civicProfessional: true }",
	"questionId": 14
}, {
	"id": 26,
	"content": "Have learned how to ask others the right questions ",
	"identifier": "B",
	"attributes": "{ civicProfessional: true }",
	"questionId": 14
}, {
	"id": 27,
	"content": "Compare it to issues I have faced in other settings",
	"identifier": "C",
	"attributes": "{ civicProfessional: true }",
	"questionId": 14
}, {
	"id": 28,
	"content": "Quit",
	"identifier": "D",
	"attributes": "{ civicProfessional: false }",
	"questionId": 14
}, {
	"id": 29,
	"content": "Draw on past experiences that have helped develop my communications skills",
	"identifier": "A",
	"attributes": "{ civicProfessional: true }",
	"questionId": 15
}, {
	"id": 30,
	"content": "Have learned how to listen, ask questions, and find the best way path in each situation",
	"identifier": "B",
	"attributes": "{ civicProfessional: true }",
	"questionId": 15
}, {
	"id": 31,
	"content": "Think about how I have communicated similar messages in the past",
	"identifier": "C",
	"attributes": "{ civicProfessional: true }",
	"questionId": 15
}, {
	"id": 32,
	"content": "Yell",
	"identifier": "D",
	"attributes": "{ civicProfessional: false }",
	"questionId": 15
}]